course/cse241/adder.v
module ex2_1;
    /* gate level model to implement an adder */
    
    wire [3:0] sum, inA, inB;
    wire       carry;
    
    adder4 a4 (sum, carry, inA, inB);
    adderTest at (inA, inB, sum, carry);
endmodule


module adder4 (sum, carry, inA, inB);
    output [3:0] sum;
    output carry;
    input [3:0] inA, inB;
    
    adder1 a0 (sum[0], c0,    inA[0], inB[0], 1'b0);
    adder1 a1 (sum[1], c1,    inA[1], inB[1], c0);
    adder1 a2 (sum[2], c2,    inA[2], inB[2], c1);
    adder1 a3 (sum[3], carry, inA[3], inB[3], c2);
endmodule


module adder1 (s, cout, a, b, cin);  
    output s, cout;
    input a, b, cin;
    
    xor (t1, a, b);
    xor (s, t1, cin);
    and (t2, t1, cin),
        (t3, a, b);
    or  (cout, t2, t3);
endmodule


module adderTest (A, B, sum, carry);
    output [3:0] A, B;
    input [3:0] sum;
    input carry;
    reg [3:0] A, B;
    
    integer i, j;
    initial begin
       $monitor ("A: %d  B: %d sum: %d  carry: %d", A, B, sum, carry);
       $dumpfile("adder_wv.vcd");
       $dumpvars;
       
       for (i=0; i<16; i=i+1) for (j=0; j<16; j=j+1) 
        begin A=i; B=j; #1 ;end 
       $finish; 
    end 
endmodule

course/cse241/adder_wv.vcd
$date
	Mon Nov 25 19:27:18 2013
$end
$version
	Icarus Verilog
$end
$timescale
	1s
$end
$scope module ex2_1 $end
$var wire 1 ! carry $end
$var wire 4 " inA [3:0] $end
$var wire 4 # inB [3:0] $end
$var wire 4 $ sum [3:0] $end
$scope module a4 $end
$var wire 1 % c0 $end
$var wire 1 & c1 $end
$var wire 1 ' c2 $end
$var wire 1 ! carry $end
$var wire 4 ( inA [3:0] $end
$var wire 4 ) inB [3:0] $end
$var wire 4 * sum [3:0] $end
$scope module a0 $end
$var wire 1 + a $end
$var wire 1 , b $end
$var wire 1 - cin $end
$var wire 1 % cout $end
$var wire 1 . s $end
$var wire 1 / t1 $end
$var wire 1 0 t2 $end
$var wire 1 1 t3 $end
$upscope $end
$scope module a1 $end
$var wire 1 2 a $end
$var wire 1 3 b $end
$var wire 1 % cin $end
$var wire 1 & cout $end
$var wire 1 4 s $end
$var wire 1 5 t1 $end
$var wire 1 6 t2 $end
$var wire 1 7 t3 $end
$upscope $end
$scope module a2 $end
$var wire 1 8 a $end
$var wire 1 9 b $end
$var wire 1 & cin $end
$var wire 1 ' cout $end
$var wire 1 : s $end
$var wire 1 ; t1 $end
$var wire 1 < t2 $end
$var wire 1 = t3 $end
$upscope $end
$scope module a3 $end
$var wire 1 > a $end
$var wire 1 ? b $end
$var wire 1 ' cin $end
$var wire 1 ! cout $end
$var wire 1 @ s $end
$var wire 1 A t1 $end
$var wire 1 B t2 $end
$var wire 1 C t3 $end
$upscope $end
$upscope $end
$scope module at $end
$var wire 1 ! carry $end
$var wire 4 D sum [3:0] $end
$var reg 4 E A [3:0] $end
$var reg 4 F B [3:0] $end
$var integer 32 G i [31:0] $end
$var integer 32 H j [31:0] $end
$upscope $end
$upscope $end
$enddefinitions $end
#0
$dumpvars
b0 H
b0 G
b0 F
b0 E
b0 D
0C
0B
0A
0@
0?
0>
0=
0<
0;
0:
09
08
07
06
05
04
03
02
01
00
0/
0.
0-
0,
0+
b0 *
b0 )
b0 (
0'
0&
0%
b0 $
b0 #
b0 "
0!
$end
#1
1.
b1 $
b1 *
b1 D
1/
1,
b1 F
b1 #
b1 )
b1 H
#2
14
0.
b10 $
b10 *
b10 D
15
0/
13
0,
b10 F
b10 #
b10 )
b10 H
#3
1.
b11 $
b11 *
b11 D
1/
1,
b11 F
b11 #
b11 )
b11 H
#4
1:
04
0.
b100 $
b100 *
b100 D
1;
05
0/
19
03
0,
b100 F
b100 #
b100 )
b100 H
#5
1.
b101 $
b101 *
b101 D
1/
1,
b101 F
b101 #
b101 )
b101 H
#6
14
0.
b110 $
b110 *
b110 D
15
0/
13
0,
b110 F
b110 #
b110 )
b110 H
#7
1.
b111 $
b111 *
b111 D
1/
1,
b111 F
b111 #
b111 )
b111 H
#8
1@
0:
04
0.
b1000 $
b1000 *
b1000 D
1A
0;
05
0/
1?
09
03
0,
b1000 F
b1000 #
b1000 )
b1000 H
#9
1.
b1001 $
b1001 *
b1001 D
1/
1,
b1001 F
b1001 #
b1001 )
b1001 H
#10
14
0.
b1010 $
b1010 *
b1010 D
15
0/
13
0,
b1010 F
b1010 #
b1010 )
b1010 H
#11
1.
b1011 $
b1011 *
b1011 D
1/
1,
b1011 F
b1011 #
b1011 )
b1011 H
#12
1:
04
0.
b1100 $
b1100 *
b1100 D
1;
05
0/
19
03
0,
b1100 F
b1100 #
b1100 )
b1100 H
#13
1.
b1101 $
b1101 *
b1101 D
1/
1,
b1101 F
b1101 #
b1101 )
b1101 H
#14
14
0.
b1110 $
b1110 *
b1110 D
15
0/
13
0,
b1110 F
b1110 #
b1110 )
b1110 H
#15
1.
b1111 $
b1111 *
b1111 D
1/
1,
b1111 F
b1111 #
b1111 )
b1111 H
#16
0@
0:
04
b1 $
b1 *
b1 D
0A
0;
05
0?
09
03
0,
1+
b0 F
b0 #
b0 )
b1 E
b1 "
b1 (
b1 G
b0 H
#17
14
0.
b10 $
b10 *
b10 D
1%
0/
11
1,
b1 F
b1 #
b1 )
b1 H
#18
1.
b11 $
b11 *
b11 D
0%
15
1/
01
13
0,
b10 F
b10 #
b10 )
b10 H
#19
1:
1&
04
16
0.
b100 $
b100 *
b100 D
1%
0/
11
1,
b11 F
b11 #
b11 )
b11 H
#20
0@
0'
0&
1:
0<
06
1.
b101 $
b101 *
b101 D
0%
1;
05
1/
01
19
03
0,
b100 F
b100 #
b100 )
b100 H
#21
14
0.
b110 $
b110 *
b110 D
1%
0/
11
1,
b101 F
b101 #
b101 )
b101 H
#22
1.
b111 $
b111 *
b111 D
0%
15
1/
01
13
0,
b110 F
b110 #
b110 )
b110 H
#23
1@
1'
0:
1<
1&
04
16
0.
b1000 $
b1000 *
b1000 D
1%
0/
11
1,
b111 F
b111 #
b111 )
b111 H
#24
0!
0'
0&
1@
0B
0:
0<
06
1.
b1001 $
b1001 *
b1001 D
0%
1A
0;
05
1/
01
1?
09
03
0,
b1000 F
b1000 #
b1000 )
b1000 H
#25
14
0.
b1010 $
b1010 *
b1010 D
1%
0/
11
1,
b1001 F
b1001 #
b1001 )
b1001 H
#26
1.
b1011 $
b1011 *
b1011 D
0%
15
1/
01
13
0,
b1010 F
b1010 #
b1010 )
b1010 H
#27
1:
1&
04
16
0.
b1100 $
b1100 *
b1100 D
1%
0/
11
1,
b1011 F
b1011 #
b1011 )
b1011 H
#28
0!
1@
0B
0'
0&
1:
0<
06
1.
b1101 $
b1101 *
b1101 D
0%
1;
05
1/
01
19
03
0,
b1100 F
b1100 #
b1100 )
b1100 H
#29
14
0.
b1110 $
b1110 *
b1110 D
1%
0/
11
1,
b1101 F
b1101 #
b1101 )
b1101 H
#30
1.
b1111 $
b1111 *
b1111 D
0%
15
1/
01
13
0,
b1110 F
b1110 #
b1110 )
b1110 H
#31
1!
0@
1B
1'
0:
1<
1&
04
16
0.
b0 $
b0 *
b0 D
1%
0/
11
1,
b1111 F
b1111 #
b1111 )
b1111 H
#32
0&
0!
0'
14
06
0@
0B
0:
b10 $
b10 *
b10 D
0<
0%
0A
0;
01
0?
09
03
0,
12
0+
b0 F
b0 #
b0 )
b10 E
b10 "
b10 (
b10 G
b0 H
#33
1.
b11 $
b11 *
b11 D
1/
1,
b1 F
b1 #
b1 )
b1 H
#34
1:
04
1&
0.
b100 $
b100 *
b100 D
05
17
0/
13
0,
b10 F
b10 #
b10 )
b10 H
#35
1.
b101 $
b101 *
b101 D
1/
1,
b11 F
b11 #
b11 )
b11 H
#36
14
0&
0.
b110 $
b110 *
b110 D
1;
15
07
0/
19
03
0,
b100 F
b100 #
b100 )
b100 H
#37
1.
b111 $
b111 *
b111 D
1/
1,
b101 F
b101 #
b101 )
b101 H
#38
1@
1'
0:
1<
04
1&
0.
b1000 $
b1000 *
b1000 D
05
17
0/
13
0,
b110 F
b110 #
b110 )
b110 H
#39
1.
b1001 $
b1001 *
b1001 D
1/
1,
b111 F
b111 #
b111 )
b111 H
#40
0!
0'
1@
0B
0<
14
0&
0.
b1010 $
b1010 *
b1010 D
1A
0;
15
07
0/
1?
09
03
0,
b1000 F
b1000 #
b1000 )
b1000 H
#41
1.
b1011 $
b1011 *
b1011 D
1/
1,
b1001 F
b1001 #
b1001 )
b1001 H
#42
1:
04
1&
0.
b1100 $
b1100 *
b1100 D
05
17
0/
13
0,
b1010 F
b1010 #
b1010 )
b1010 H
#43
1.
b1101 $
b1101 *
b1101 D
1/
1,
b1011 F
b1011 #
b1011 )
b1011 H
#44
14
0&
0.
b1110 $
b1110 *
b1110 D
1;
15
07
0/
19
03
0,
b1100 F
b1100 #
b1100 )
b1100 H
#45
1.
b1111 $
b1111 *
b1111 D
1/
1,
b1101 F
b1101 #
b1101 )
b1101 H
#46
1!
0@
1B
1'
0:
1<
04
1&
0.
b0 $
b0 *
b0 D
05
17
0/
13
0,
b1110 F
b1110 #
b1110 )
b1110 H
#47
1.
b1 $
b1 *
b1 D
1/
1,
b1111 F
b1111 #
b1111 )
b1111 H
#48
0!
0'
0@
0B
0<
14
b11 $
b11 *
b11 D
0&
0A
0;
15
07
0?
09
03
0,
1+
b0 F
b0 #
b0 )
b11 E
b11 "
b11 (
b11 G
b0 H
#49
1:
1&
04
16
0.
b100 $
b100 *
b100 D
1%
0/
11
1,
b1 F
b1 #
b1 )
b1 H
#50
06
1.
b101 $
b101 *
b101 D
0%
05
17
1/
01
13
0,
b10 F
b10 #
b10 )
b10 H
#51
14
0.
b110 $
b110 *
b110 D
1%
0/
11
1,
b11 F
b11 #
b11 )
b11 H
#52
0&
1.
b111 $
b111 *
b111 D
0%
1;
15
07
1/
01
19
03
0,
b100 F
b100 #
b100 )
b100 H
#53
1@
1'
0:
1<
1&
04
16
0.
b1000 $
b1000 *
b1000 D
1%
0/
11
1,
b101 F
b101 #
b101 )
b101 H
#54
06
1.
b1001 $
b1001 *
b1001 D
0%
05
17
1/
01
13
0,
b110 F
b110 #
b110 )
b110 H
#55
14
0.
b1010 $
b1010 *
b1010 D
1%
0/
11
1,
b111 F
b111 #
b111 )
b111 H
#56
0!
0'
1@
0B
0<
0&
1.
b1011 $
b1011 *
b1011 D
0%
1A
0;
15
07
1/
01
1?
09
03
0,
b1000 F
b1000 #
b1000 )
b1000 H
#57
1:
1&
04
16
0.
b1100 $
b1100 *
b1100 D
1%
0/
11
1,
b1001 F
b1001 #
b1001 )
b1001 H
#58
06
1.
b1101 $
b1101 *
b1101 D
0%
05
17
1/
01
13
0,
b1010 F
b1010 #
b1010 )
b1010 H
#59
14
0.
b1110 $
b1110 *
b1110 D
1%
0/
11
1,
b1011 F
b1011 #
b1011 )
b1011 H
#60
0&
1.
b1111 $
b1111 *
b1111 D
0%
1;
15
07
1/
01
19
03
0,
b1100 F
b1100 #
b1100 )
b1100 H
#61
1!
0@
1B
1'
0:
1<
1&
04
16
0.
b0 $
b0 *
b0 D
1%
0/
11
1,
b1101 F
b1101 #
b1101 )
b1101 H
#62
06
1.
b1 $
b1 *
b1 D
0%
05
17
1/
01
13
0,
b1110 F
b1110 #
b1110 )
b1110 H
#63
14
0.
b10 $
b10 *
b10 D
1%
0/
11
1,
b1111 F
b1111 #
b1111 )
b1111 H
#64
0'
0!
1:
0<
04
0@
b100 $
b100 *
b100 D
0B
0&
0%
0A
07
01
0?
09
03
0,
18
02
0+
b0 F
b0 #
b0 )
b100 E
b100 "
b100 (
b100 G
b0 H
#65
1.
b101 $
b101 *
b101 D
1/
1,
b1 F
b1 #
b1 )
b1 H
#66
14
0.
b110 $
b110 *
b110 D
15
0/
13
0,
b10 F
b10 #
b10 )
b10 H
#67
1.
b111 $
b111 *
b111 D
1/
1,
b11 F
b11 #
b11 )
b11 H
#68
1@
0:
1'
04
0.
b1000 $
b1000 *
b1000 D
0;
1=
05
0/
19
03
0,
b100 F
b100 #
b100 )
b100 H
#69
1.
b1001 $
b1001 *
b1001 D
1/
1,
b101 F
b101 #
b101 )
b101 H
#70
14
0.
b1010 $
b1010 *
b1010 D
15
0/
13
0,
b110 F
b110 #
b110 )
b110 H
#71
1.
b1011 $
b1011 *
b1011 D
1/
1,
b111 F
b111 #
b111 )
b111 H
#72
1:
0'
04
0.
b1100 $
b1100 *
b1100 D
1A
1;
0=
05
0/
1?
09
03
0,
b1000 F
b1000 #
b1000 )
b1000 H
#73
1.
b1101 $
b1101 *
b1101 D
1/
1,
b1001 F
b1001 #
b1001 )
b1001 H
#74
14
0.
b1110 $
b1110 *
b1110 D
15
0/
13
0,
b1010 F
b1010 #
b1010 )
b1010 H
#75
1.
b1111 $
b1111 *
b1111 D
1/
1,
b1011 F
b1011 #
b1011 )
b1011 H
#76
1!
0@
1B
0:
1'
04
0.
b0 $
b0 *
b0 D
0;
1=
05
0/
19
03
0,
b1100 F
b1100 #
b1100 )
b1100 H
#77
1.
b1 $
b1 *
b1 D
1/
1,
b1101 F
b1101 #
b1101 )
b1101 H
#78
14
0.
b10 $
b10 *
b10 D
15
0/
13
0,
b1110 F
b1110 #
b1110 )
b1110 H
#79
1.
b11 $
b11 *
b11 D
1/
1,
b1111 F
b1111 #
b1111 )
b1111 H
#80
0!
0B
1:
0'
04
b101 $
b101 *
b101 D
0A
1;
0=
05
0?
09
03
0,
1+
b0 F
b0 #
b0 )
b101 E
b101 "
b101 (
b101 G
b0 H
#81
14
0.
b110 $
b110 *
b110 D
1%
0/
11
1,
b1 F
b1 #
b1 )
b1 H
#82
1.
b111 $
b111 *
b111 D
0%
15
1/
01
13
0,
b10 F
b10 #
b10 )
b10 H
#83
1@
1'
0:
1<
1&
04
16
0.
b1000 $
b1000 *
b1000 D
1%
0/
11
1,
b11 F
b11 #
b11 )
b11 H
#84
0&
0:
0<
06
1.
b1001 $
b1001 *
b1001 D
0%
0;
1=
05
1/
01
19
03
0,
b100 F
b100 #
b100 )
b100 H
#85
14
0.
b1010 $
b1010 *
b1010 D
1%
0/
11
1,
b101 F
b101 #
b101 )
b101 H
#86
1.
b1011 $
b1011 *
b1011 D
0%
15
1/
01
13
0,
b110 F
b110 #
b110 )
b110 H
#87
1:
1&
04
16
0.
b1100 $
b1100 *
b1100 D
1%
0/
11
1,
b111 F
b111 #
b111 )
b111 H
#88
0!
1@
0B
0&
1:
0<
0'
06
1.
b1101 $
b1101 *
b1101 D
0%
1A
1;
0=
05
1/
01
1?
09
03
0,
b1000 F
b1000 #
b1000 )
b1000 H
#89
14
0.
b1110 $
b1110 *
b1110 D
1%
0/
11
1,
b1001 F
b1001 #
b1001 )
b1001 H
#90
1.
b1111 $
b1111 *
b1111 D
0%
15
1/
01
13
0,
b1010 F
b1010 #
b1010 )
b1010 H
#91
1!
0@
1B
1'
0:
1<
1&
04
16
0.
b0 $
b0 *
b0 D
1%
0/
11
1,
b1011 F
b1011 #
b1011 )
b1011 H
#92
0&
0:
0<
06
1.
b1 $
b1 *
b1 D
0%
0;
1=
05
1/
01
19
03
0,
b1100 F
b1100 #
b1100 )
b1100 H
#93
14
0.
b10 $
b10 *
b10 D
1%
0/
11
1,
b1101 F
b1101 #
b1101 )
b1101 H
#94
1.
b11 $
b11 *
b11 D
0%
15
1/
01
13
0,
b1110 F
b1110 #
b1110 )
b1110 H
#95
1:
1&
04
16
0.
b100 $
b100 *
b100 D
1%
0/
11
1,
b1111 F
b1111 #
b1111 )
b1111 H
#96
0@
0&
0!
14
06
0B
1:
b110 $
b110 *
b110 D
0<
0'
0%
0A
1;
0=
01
0?
09
03
0,
12
0+
b0 F
b0 #
b0 )
b110 E
b110 "
b110 (
b110 G
b0 H
#97
1.
b111 $
b111 *
b111 D
1/
1,
b1 F
b1 #
b1 )
b1 H
#98
1@
1'
0:
1<
04
1&
0.
b1000 $
b1000 *
b1000 D
05
17
0/
13
0,
b10 F
b10 #
b10 )
b10 H
#99
1.
b1001 $
b1001 *
b1001 D
1/
1,
b11 F
b11 #
b11 )
b11 H
#100
0<
14
0&
0.
b1010 $
b1010 *
b1010 D
0;
1=
15
07
0/
19
03
0,
b100 F
b100 #
b100 )
b100 H
#101
1.
b1011 $
b1011 *
b1011 D
1/
1,
b101 F
b101 #
b101 )
b101 H
#102
1:
04
1&
0.
b1100 $
b1100 *
b1100 D
05
17
0/
13
0,
b110 F
b110 #
b110 )
b110 H
#103
1.
b1101 $
b1101 *
b1101 D
1/
1,
b111 F
b111 #
b111 )
b111 H
#104
0'
14
0&
0.
b1110 $
b1110 *
b1110 D
1A
1;
0=
15
07
0/
1?
09
03
0,
b1000 F
b1000 #
b1000 )
b1000 H
#105
1.
b1111 $
b1111 *
b1111 D
1/
1,
b1001 F
b1001 #
b1001 )
b1001 H
#106
1!
0@
1B
1'
0:
1<
04
1&
0.
b0 $
b0 *
b0 D
05
17
0/
13
0,
b1010 F
b1010 #
b1010 )
b1010 H
#107
1.
b1 $
b1 *
b1 D
1/
1,
b1011 F
b1011 #
b1011 )
b1011 H
#108
0<
14
0&
0.
b10 $
b10 *
b10 D
0;
1=
15
07
0/
19
03
0,
b1100 F
b1100 #
b1100 )
b1100 H
#109
1.
b11 $
b11 *
b11 D
1/
1,
b1101 F
b1101 #
b1101 )
b1101 H
#110
1:
04
1&
0.
b100 $
b100 *
b100 D
05
17
0/
13
0,
b1110 F
b1110 #
b1110 )
b1110 H
#111
1.
b101 $
b101 *
b101 D
1/
1,
b1111 F
b1111 #
b1111 )
b1111 H
#112
0!
0B
0'
14
b111 $
b111 *
b111 D
0&
0A
1;
0=
15
07
0?
09
03
0,
1+
b0 F
b0 #
b0 )
b111 E
b111 "
b111 (
b111 G
b0 H
#113
1@
1'
0:
1<
1&
04
16
0.
b1000 $
b1000 *
b1000 D
1%
0/
11
1,
b1 F
b1 #
b1 )
b1 H
#114
06
1.
b1001 $
b1001 *
b1001 D
0%
05
17
1/
01
13
0,
b10 F
b10 #
b10 )
b10 H
#115
14
0.
b1010 $
b1010 *
b1010 D
1%
0/
11
1,
b11 F
b11 #
b11 )
b11 H
#116
0<
0&
1.
b1011 $
b1011 *
b1011 D
0%
0;
1=
15
07
1/
01
19
03
0,
b100 F
b100 #
b100 )
b100 H
#117
1:
1&
04
16
0.
b1100 $
b1100 *
b1100 D
1%
0/
11
1,
b101 F
b101 #
b101 )
b101 H
#118
06
1.
b1101 $
b1101 *
b1101 D
0%
05
17
1/
01
13
0,
b110 F
b110 #
b110 )
b110 H
#119
14
0.
b1110 $
b1110 *
b1110 D
1%
0/
11
1,
b111 F
b111 #
b111 )
b111 H
#120
0'
0&
1.
b1111 $
b1111 *
b1111 D
0%
1A
1;
0=
15
07
1/
01
1?
09
03
0,
b1000 F
b1000 #
b1000 )
b1000 H
#121
1!
0@
1B
1'
0:
1<
1&
04
16
0.
b0 $
b0 *
b0 D
1%
0/
11
1,
b1001 F
b1001 #
b1001 )
b1001 H
#122
06
1.
b1 $
b1 *
b1 D
0%
05
17
1/
01
13
0,
b1010 F
b1010 #
b1010 )
b1010 H
#123
14
0.
b10 $
b10 *
b10 D
1%
0/
11
1,
b1011 F
b1011 #
b1011 )
b1011 H
#124
0<
0&
1.
b11 $
b11 *
b11 D
0%
0;
1=
15
07
1/
01
19
03
0,
b1100 F
b1100 #
b1100 )
b1100 H
#125
1:
1&
04
16
0.
b100 $
b100 *
b100 D
1%
0/
11
1,
b1101 F
b1101 #
b1101 )
b1101 H
#126
06
1.
b101 $
b101 *
b101 D
0%
05
17
1/
01
13
0,
b1110 F
b1110 #
b1110 )
b1110 H
#127
14
0.
b110 $
b110 *
b110 D
1%
0/
11
1,
b1111 F
b1111 #
b1111 )
b1111 H
#128
0!
1@
0B
0:
04
b1000 $
b1000 *
b1000 D
0'
0&
0%
0=
07
01
0?
09
03
0,
1>
08
02
0+
b0 F
b0 #
b0 )
b1000 E
b1000 "
b1000 (
b1000 G
b0 H
#129
1.
b1001 $
b1001 *
b1001 D
1/
1,
b1 F
b1 #
b1 )
b1 H
#130
14
0.
b1010 $
b1010 *
b1010 D
15
0/
13
0,
b10 F
b10 #
b10 )
b10 H
#131
1.
b1011 $
b1011 *
b1011 D
1/
1,
b11 F
b11 #
b11 )
b11 H
#132
1:
04
0.
b1100 $
b1100 *
b1100 D
1;
05
0/
19
03
0,
b100 F
b100 #
b100 )
b100 H
#133
1.
b1101 $
b1101 *
b1101 D
1/
1,
b101 F
b101 #
b101 )
b101 H
#134
14
0.
b1110 $
b1110 *
b1110 D
15
0/
13
0,
b110 F
b110 #
b110 )
b110 H
#135
1.
b1111 $
b1111 *
b1111 D
1/
1,
b111 F
b111 #
b111 )
b111 H
#136
0@
1!
0:
04
0.
b0 $
b0 *
b0 D
0A
1C
0;
05
0/
1?
09
03
0,
b1000 F
b1000 #
b1000 )
b1000 H
#137
1.
b1 $
b1 *
b1 D
1/
1,
b1001 F
b1001 #
b1001 )
b1001 H
#138
14
0.
b10 $
b10 *
b10 D
15
0/
13
0,
b1010 F
b1010 #
b1010 )
b1010 H
#139
1.
b11 $
b11 *
b11 D
1/
1,
b1011 F
b1011 #
b1011 )
b1011 H
#140
1:
04
0.
b100 $
b100 *
b100 D
1;
05
0/
19
03
0,
b1100 F
b1100 #
b1100 )
b1100 H
#141
1.
b101 $
b101 *
b101 D
1/
1,
b1101 F
b1101 #
b1101 )
b1101 H
#142
14
0.
b110 $
b110 *
b110 D
15
0/
13
0,
b1110 F
b1110 #
b1110 )
b1110 H
#143
1.
b111 $
b111 *
b111 D
1/
1,
b1111 F
b1111 #
b1111 )
b1111 H
#144
1@
0!
0:
04
b1001 $
b1001 *
b1001 D
1A
0C
0;
05
0?
09
03
0,
1+
b0 F
b0 #
b0 )
b1001 E
b1001 "
b1001 (
b1001 G
b0 H
#145
14
0.
b1010 $
b1010 *
b1010 D
1%
0/
11
1,
b1 F
b1 #
b1 )
b1 H
#146
1.
b1011 $
b1011 *
b1011 D
0%
15
1/
01
13
0,
b10 F
b10 #
b10 )
b10 H
#147
1:
1&
04
16
0.
b1100 $
b1100 *
b1100 D
1%
0/
11
1,
b11 F
b11 #
b11 )
b11 H
#148
0!
1@
0B
0'
0&
1:
0<
06
1.
b1101 $
b1101 *
b1101 D
0%
1;
05
1/
01
19
03
0,
b100 F
b100 #
b100 )
b100 H
#149
14
0.
b1110 $
b1110 *
b1110 D
1%
0/
11
1,
b101 F
b101 #
b101 )
b101 H
#150
1.
b1111 $
b1111 *
b1111 D
0%
15
1/
01
13
0,
b110 F
b110 #
b110 )
b110 H
#151
1!
0@
1B
1'
0:
1<
1&
04
16
0.
b0 $
b0 *
b0 D
1%
0/
11
1,
b111 F
b111 #
b111 )
b111 H
#152
0'
0&
0@
0B
0:
0<
06
1.
b1 $
b1 *
b1 D
0%
0A
1C
0;
05
1/
01
1?
09
03
0,
b1000 F
b1000 #
b1000 )
b1000 H
#153
14
0.
b10 $
b10 *
b10 D
1%
0/
11
1,
b1001 F
b1001 #
b1001 )
b1001 H
#154
1.
b11 $
b11 *
b11 D
0%
15
1/
01
13
0,
b1010 F
b1010 #
b1010 )
b1010 H
#155
1:
1&
04
16
0.
b100 $
b100 *
b100 D
1%
0/
11
1,
b1011 F
b1011 #
b1011 )
b1011 H
#156
0@
0'
0&
1:
0<
06
1.
b101 $
b101 *
b101 D
0%
1;
05
1/
01
19
03
0,
b1100 F
b1100 #
b1100 )
b1100 H
#157
14
0.
b110 $
b110 *
b110 D
1%
0/
11
1,
b1101 F
b1101 #
b1101 )
b1101 H
#158
1.
b111 $
b111 *
b111 D
0%
15
1/
01
13
0,
b1110 F
b1110 #
b1110 )
b1110 H
#159
1@
1'
0:
1<
1&
04
16
0.
b1000 $
b1000 *
b1000 D
1%
0/
11
1,
b1111 F
b1111 #
b1111 )
b1111 H
#160
0&
0'
14
06
1@
0B
0!
0:
b1010 $
b1010 *
b1010 D
0<
0%
1A
0C
0;
01
0?
09
03
0,
12
0+
b0 F
b0 #
b0 )
b1010 E
b1010 "
b1010 (
b1010 G
b0 H
#161
1.
b1011 $
b1011 *
b1011 D
1/
1,
b1 F
b1 #
b1 )
b1 H
#162
1:
04
1&
0.
b1100 $
b1100 *
b1100 D
05
17
0/
13
0,
b10 F
b10 #
b10 )
b10 H
#163
1.
b1101 $
b1101 *
b1101 D
1/
1,
b11 F
b11 #
b11 )
b11 H
#164
14
0&
0.
b1110 $
b1110 *
b1110 D
1;
15
07
0/
19
03
0,
b100 F
b100 #
b100 )
b100 H
#165
1.
b1111 $
b1111 *
b1111 D
1/
1,
b101 F
b101 #
b101 )
b101 H
#166
1!
0@
1B
1'
0:
1<
04
1&
0.
b0 $
b0 *
b0 D
05
17
0/
13
0,
b110 F
b110 #
b110 )
b110 H
#167
1.
b1 $
b1 *
b1 D
1/
1,
b111 F
b111 #
b111 )
b111 H
#168
0'
0@
0B
0<
14
0&
0.
b10 $
b10 *
b10 D
0A
1C
0;
15
07
0/
1?
09
03
0,
b1000 F
b1000 #
b1000 )
b1000 H
#169
1.
b11 $
b11 *
b11 D
1/
1,
b1001 F
b1001 #
b1001 )
b1001 H
#170
1:
04
1&
0.
b100 $
b100 *
b100 D
05
17
0/
13
0,
b1010 F
b1010 #
b1010 )
b1010 H
#171
1.
b101 $
b101 *
b101 D
1/
1,
b1011 F
b1011 #
b1011 )
b1011 H
#172
14
0&
0.
b110 $
b110 *
b110 D
1;
15
07
0/
19
03
0,
b1100 F
b1100 #
b1100 )
b1100 H
#173
1.
b111 $
b111 *
b111 D
1/
1,
b1101 F
b1101 #
b1101 )
b1101 H
#174
1@
1'
0:
1<
04
1&
0.
b1000 $
b1000 *
b1000 D
05
17
0/
13
0,
b1110 F
b1110 #
b1110 )
b1110 H
#175
1.
b1001 $
b1001 *
b1001 D
1/
1,
b1111 F
b1111 #
b1111 )
b1111 H
#176
0'
1@
0B
0!
0<
14
b1011 $
b1011 *
b1011 D
0&
1A
0C
0;
15
07
0?
09
03
0,
1+
b0 F
b0 #
b0 )
b1011 E
b1011 "
b1011 (
b1011 G
b0 H
#177
1:
1&
04
16
0.
b1100 $
b1100 *
b1100 D
1%
0/
11
1,
b1 F
b1 #
b1 )
b1 H
#178
06
1.
b1101 $
b1101 *
b1101 D
0%
05
17
1/
01
13
0,
b10 F
b10 #
b10 )
b10 H
#179
14
0.
b1110 $
b1110 *
b1110 D
1%
0/
11
1,
b11 F
b11 #
b11 )
b11 H
#180
0&
1.
b1111 $
b1111 *
b1111 D
0%
1;
15
07
1/
01
19
03
0,
b100 F
b100 #
b100 )
b100 H
#181
1!
0@
1B
1'
0:
1<
1&
04
16
0.
b0 $
b0 *
b0 D
1%
0/
11
1,
b101 F
b101 #
b101 )
b101 H
#182
06
1.
b1 $
b1 *
b1 D
0%
05
17
1/
01
13
0,
b110 F
b110 #
b110 )
b110 H
#183
14
0.
b10 $
b10 *
b10 D
1%
0/
11
1,
b111 F
b111 #
b111 )
b111 H
#184
0'
0@
0B
0<
0&
1.
b11 $
b11 *
b11 D
0%
0A
1C
0;
15
07
1/
01
1?
09
03
0,
b1000 F
b1000 #
b1000 )
b1000 H
#185
1:
1&
04
16
0.
b100 $
b100 *
b100 D
1%
0/
11
1,
b1001 F
b1001 #
b1001 )
b1001 H
#186
06
1.
b101 $
b101 *
b101 D
0%
05
17
1/
01
13
0,
b1010 F
b1010 #
b1010 )
b1010 H
#187
14
0.
b110 $
b110 *
b110 D
1%
0/
11
1,
b1011 F
b1011 #
b1011 )
b1011 H
#188
0&
1.
b111 $
b111 *
b111 D
0%
1;
15
07
1/
01
19
03
0,
b1100 F
b1100 #
b1100 )
b1100 H
#189
1@
1'
0:
1<
1&
04
16
0.
b1000 $
b1000 *
b1000 D
1%
0/
11
1,
b1101 F
b1101 #
b1101 )
b1101 H
#190
06
1.
b1001 $
b1001 *
b1001 D
0%
05
17
1/
01
13
0,
b1110 F
b1110 #
b1110 )
b1110 H
#191
14
0.
b1010 $
b1010 *
b1010 D
1%
0/
11
1,
b1111 F
b1111 #
b1111 )
b1111 H
#192
0'
1:
0<
04
1@
b1100 $
b1100 *
b1100 D
0B
0!
0&
0%
1A
0C
07
01
0?
09
03
0,
18
02
0+
b0 F
b0 #
b0 )
b1100 E
b1100 "
b1100 (
b1100 G
b0 H
#193
1.
b1101 $
b1101 *
b1101 D
1/
1,
b1 F
b1 #
b1 )
b1 H
#194
14
0.
b1110 $
b1110 *
b1110 D
15
0/
13
0,
b10 F
b10 #
b10 )
b10 H
#195
1.
b1111 $
b1111 *
b1111 D
1/
1,
b11 F
b11 #
b11 )
b11 H
#196
1!
0@
1B
0:
1'
04
0.
b0 $
b0 *
b0 D
0;
1=
05
0/
19
03
0,
b100 F
b100 #
b100 )
b100 H
#197
1.
b1 $
b1 *
b1 D
1/
1,
b101 F
b101 #
b101 )
b101 H
#198
14
0.
b10 $
b10 *
b10 D
15
0/
13
0,
b110 F
b110 #
b110 )
b110 H
#199
1.
b11 $
b11 *
b11 D
1/
1,
b111 F
b111 #
b111 )
b111 H
#200
0B
1:
0'
04
0.
b100 $
b100 *
b100 D
0A
1C
1;
0=
05
0/
1?
09
03
0,
b1000 F
b1000 #
b1000 )
b1000 H
#201
1.
b101 $
b101 *
b101 D
1/
1,
b1001 F
b1001 #
b1001 )
b1001 H
#202
14
0.
b110 $
b110 *
b110 D
15
0/
13
0,
b1010 F
b1010 #
b1010 )
b1010 H
#203
1.
b111 $
b111 *
b111 D
1/
1,
b1011 F
b1011 #
b1011 )
b1011 H
#204
1@
0:
1'
04
0.
b1000 $
b1000 *
b1000 D
0;
1=
05
0/
19
03
0,
b1100 F
b1100 #
b1100 )
b1100 H
